cybergis_compute_client/Client.py
cybergis_compute_client/CyberGISCompute.py
cybergis_compute_client/Job.py
cybergis_compute_client/MarkdownTable.py
cybergis_compute_client/UI.py
cybergis_compute_client/Zip.py
cybergis_compute_client/__init__.py
test/UI_test_cases.py
test/__init__.py
test/test_cases.py
cybergis_compute_client-0.2.4.dist-info/LICENSE
cybergis_compute_client-0.2.4.dist-info/METADATA
cybergis_compute_client-0.2.4.dist-info/WHEEL
cybergis_compute_client-0.2.4.dist-info/top_level.txt
cybergis_compute_client-0.2.4.dist-info/RECORD
