Metadata-Version: 2.1
Name: cybergis-compute-client
Version: 0.2.4
Summary: CyberGISX compatable HPC job submission client
Home-page: https://github.com/cybergis/cybergis-compute-python-sdk
Author: CyberGIS Center
Author-email: help@cybergis.org
License: Apache License 2.0
Keywords: HPC
Classifier: Development Status :: 4 - Beta
Classifier: Operating System :: OS Independent
Classifier: License :: OSI Approved :: Apache Software License
Classifier: Intended Audience :: Science/Research
Classifier: Topic :: Software Development :: Build Tools
Classifier: Topic :: Scientific/Engineering :: GIS
Classifier: Topic :: Scientific/Engineering :: Information Analysis
Classifier: Programming Language :: Python :: 3
License-File: LICENSE
Requires-Dist: ipython (==8.3.0)
Requires-Dist: ipyfilechooser
Requires-Dist: jupyterlab-widgets (==1.1.0)
